temp_pkg_20230523_4mbl/__about__.py
temp_pkg_20230523_4mbl/__init__.py
temp_pkg_20230523_4mbl-0.0.1.dist-info/METADATA
temp_pkg_20230523_4mbl-0.0.1.dist-info/WHEEL
temp_pkg_20230523_4mbl-0.0.1.dist-info/licenses/LICENSE.txt
temp_pkg_20230523_4mbl-0.0.1.dist-info/RECORD
